{
  "users": [
    {
      "name": "nguyen van hong",
      "phoneNumber": "09263232",
      "id": "Yz6WC68i1"
    },
    {
      "name": "nguyễn văn Nam",
      "phoneNumber": "09263232",
      "id": "vHYEOAHav"
    },
    {
      "name": "",
      "phoneNumber": "",
      "id": "iuqXSO-I_"
    },
    {
      "name": "nguyễn văn Nam",
      "phoneNumber": "09263232",
      "id": "joixURQh2"
    },
    {
      "name": "nguyen van a",
      "phoneNumber": "02927362",
      "id": "IQVLvRY3S"
    }
  ]
}